radinNFP/__init__.py
Radinfp1-0.0.1.dist-info/METADATA
Radinfp1-0.0.1.dist-info/WHEEL
Radinfp1-0.0.1.dist-info/top_level.txt
Radinfp1-0.0.1.dist-info/RECORD
